{
    "version": "https://jsonfeed.org/version/1",
    "title": "NixOS Package PRs for kfilemetadata-5.106.0, kidletime-5.106.0, baloo, kxmlrpcclient, libkscreen, kscreenlocker packages",
    "home_page_url": "https://pbek.github.io/github-search-rss/nixos-packages-13.json",
    "feed_url": "https://pbek.github.io/github-search-rss/nixos-packages-13.json",
    "description": "NixOS Package PRs for kfilemetadata-5.106.0, kidletime-5.106.0, baloo, kxmlrpcclient, libkscreen, kscreenlocker packages on GitHub",
    "items": []
}